manukaclient/__init__.py
manukaclient/client.py
manukaclient/osc/__init__.py
manukaclient/osc/plugin.py
manukaclient/osc/v1/__init__.py
manukaclient/osc/v1/external_ids.py
manukaclient/osc/v1/users.py
manukaclient/tests/__init__.py
manukaclient/tests/unit/__init__.py
manukaclient/tests/unit/fakes.py
manukaclient/tests/unit/v1/__init__.py
manukaclient/tests/unit/v1/fakes.py
manukaclient/tests/unit/v1/test_external_ids.py
manukaclient/tests/unit/v1/test_keystone_ext.py
manukaclient/tests/unit/v1/test_users.py
manukaclient/v1/__init__.py
manukaclient/v1/client.py
manukaclient/v1/external_ids.py
manukaclient/v1/keystone_ext.py
manukaclient/v1/users.py
manukaclient-2.1.0.dist-info/LICENSE
manukaclient-2.1.0.dist-info/METADATA
manukaclient-2.1.0.dist-info/WHEEL
manukaclient-2.1.0.dist-info/entry_points.txt
manukaclient-2.1.0.dist-info/pbr.json
manukaclient-2.1.0.dist-info/top_level.txt
manukaclient-2.1.0.dist-info/RECORD
