Metadata-Version: 2.2
Name: manukaclient
Version: 2.1.0
Summary: Client for the Nectar Account system
Home-page: https://github.com/NeCTAR-RC/python-manukaclient
Author: ARDC Nectar Cloud Services
Author-email: coreservices@ardc.edu.au
License: Apache-2.0
Keywords: manuka
Classifier: Environment :: OpenStack
Classifier: Intended Audience :: Information Technology
Classifier: Intended Audience :: System Administrators
Classifier: License :: OSI Approved :: Apache Software License
Classifier: Operating System :: POSIX :: Linux
Classifier: Programming Language :: Python
Classifier: Programming Language :: Python :: 3 :: Only
Classifier: Programming Language :: Python :: 3
Classifier: Programming Language :: Python :: 3.10
Classifier: Programming Language :: Python :: 3.12
License-File: LICENSE
Requires-Dist: oslo.utils
Requires-Dist: requests
Requires-Dist: keystoneauth1
Requires-Dist: python-keystoneclient
Requires-Dist: osc-lib
Requires-Dist: nectarclient-lib>=1.3.0
Requires-Dist: pbr
Dynamic: author
Dynamic: author-email
Dynamic: classifier
Dynamic: description
Dynamic: home-page
Dynamic: keywords
Dynamic: license
Dynamic: requires-dist
Dynamic: summary
